.gitignore
README.md
setup.py
illumination/__init__.py
illumination/cartoons.py
illumination/colors.py
illumination/imports.py
illumination/talker.py
illumination/utilities.py
illumination/version.py
illumination/wrappers.py
illumination/zoom.py
illumination.egg-info/PKG-INFO
illumination.egg-info/SOURCES.txt
illumination.egg-info/dependency_links.txt
illumination.egg-info/not-zip-safe
illumination.egg-info/requires.txt
illumination.egg-info/top_level.txt
illumination/frames/CCDFrame.py
illumination/frames/CameraFrame.py
illumination/frames/EmptyTimeseriesFrame.py
illumination/frames/FrameBase.py
illumination/frames/LocalStampFrame.py
illumination/frames/LocalZoomFrame.py
illumination/frames/ZoomFrame.py
illumination/frames/__init__.py
illumination/frames/imshowFrame.py
illumination/illustrations/CCDIllustration.py
illumination/illustrations/CameraIllustration.py
illumination/illustrations/CameraOfCCDsIllustration.py
illumination/illustrations/FourCameraIllustration.py
illumination/illustrations/FourCameraOfCCDsIllustration.py
illumination/illustrations/FourCamerasWithZooms.py
illumination/illustrations/GenericIllustration.py
illumination/illustrations/IllustrationBase.py
illumination/illustrations/SideBySideIllustration.py
illumination/illustrations/SingleCameraWithZoomIllustration.py
illumination/illustrations/StampsIllustration.py
illumination/illustrations/__init__.py
illumination/illustrations/imshowIllustration.py
illumination/postage/__init__.py
illumination/postage/cubes.py
illumination/postage/process_sparse.py
illumination/postage/stackers.py
illumination/postage/stamps.py
illumination/postage/tpf.py
illumination/postage/data/clean.py
illumination/postage/data/lc-ext0-header.txt
illumination/postage/data/lc-ext1-header.txt
illumination/postage/data/lc-ext2-header.txt
illumination/postage/data/tpf-ext0-header.txt
illumination/postage/data/tpf-ext1-header.txt
illumination/postage/data/tpf-ext2-header.txt
illumination/sandbox/__init__.py
illumination/sandbox/backgrounds/__init__.py
illumination/sandbox/backgrounds/backgrounds.py
illumination/sandbox/photometry/__init__.py
illumination/sandbox/photometry/animations.py
illumination/sandbox/photometry/cosmics.py
