Metadata-Version: 2.1
Name: illumination
Version: 0.1.0
Summary: Python tools for visualizing astronomical images, particularly from the NASA TESS mission.
Home-page: https://github.com/zkbt/illumination
Author: Zach Berta-Thompson
Author-email: zach.bertathompson@colorado.edu
License: MIT
Classifier: Intended Audience :: Education
Classifier: Intended Audience :: Science/Research
Classifier: Programming Language :: Python
Classifier: Topic :: Scientific/Engineering :: Astronomy
Requires-Python: >=3.6
Requires-Dist: numpy
Requires-Dist: matplotlib
Requires-Dist: scipy
Requires-Dist: astropy>=3.0
Provides-Extra: images
Requires-Dist: scikit-image; extra == "images"
